mizbancloud/__init__.py
mizbancloud/client.py
mizbancloud/config.py
mizbancloud/http_client.py
mizbancloud/exceptions/__init__.py
mizbancloud/modules/__init__.py
mizbancloud/modules/auth.py
mizbancloud/modules/cdn.py
mizbancloud/modules/cloud.py
mizbancloud/modules/statics.py
mizbancloud_sdk-1.0.0.dist-info/licenses/LICENSE.txt
mizbancloud_sdk-1.0.0.dist-info/METADATA
mizbancloud_sdk-1.0.0.dist-info/WHEEL
mizbancloud_sdk-1.0.0.dist-info/top_level.txt
mizbancloud_sdk-1.0.0.dist-info/RECORD
