Metadata-Version: 2.4
Name: mizbancloud-sdk
Version: 1.0.0
Summary: Official Python SDK for MizbanCloud CDN and Cloud APIs
Author-email: MizbanCloud <info@mizbancloud.com>
License: MIT
Project-URL: Homepage, https://github.com/mizbancloud/python-sdk
Project-URL: Repository, https://github.com/mizbancloud/python-sdk
Project-URL: Documentation, https://github.com/mizbancloud/python-sdk#readme
Keywords: mizbancloud,cdn,cloud,api,sdk
Classifier: Development Status :: 5 - Production/Stable
Classifier: Intended Audience :: Developers
Classifier: License :: OSI Approved :: MIT License
Classifier: Operating System :: OS Independent
Classifier: Programming Language :: Python :: 3
Classifier: Programming Language :: Python :: 3.8
Classifier: Programming Language :: Python :: 3.9
Classifier: Programming Language :: Python :: 3.10
Classifier: Programming Language :: Python :: 3.11
Classifier: Programming Language :: Python :: 3.12
Classifier: Topic :: Internet :: WWW/HTTP
Classifier: Topic :: Software Development :: Libraries :: Python Modules
Requires-Python: >=3.8
License-File: LICENSE.txt
Requires-Dist: requests>=2.25.0
Provides-Extra: dev
Requires-Dist: pytest>=7.0.0; extra == "dev"
Requires-Dist: pytest-cov>=4.0.0; extra == "dev"
Dynamic: license-file
